pytest_mock_api.py
pytest_mock_api-0.1.0.dist-info/LICENSE
pytest_mock_api-0.1.0.dist-info/METADATA
pytest_mock_api-0.1.0.dist-info/WHEEL
pytest_mock_api-0.1.0.dist-info/entry_points.txt
pytest_mock_api-0.1.0.dist-info/top_level.txt
pytest_mock_api-0.1.0.dist-info/RECORD
