Metadata-Version: 2.1
Name: pytest-mock-api
Version: 0.1.0
Summary: A mock API server with configurable routes and responses available as a fixture.
Home-page: https://github.com/gaucheph/pytest-mock-api
Author: Mark Patrick Harmon
Author-email: mpatharm@gmail.com
Maintainer: Mark Patrick Harmon
Maintainer-email: gaucheph@gmail.com
License: MIT
Platform: UNKNOWN
Classifier: Development Status :: 1 - Planning
Classifier: Framework :: Pytest
Classifier: Intended Audience :: Developers
Classifier: Topic :: Software Development :: Testing
Classifier: Programming Language :: Python
Classifier: Programming Language :: Python :: 3.6
Classifier: Programming Language :: Python :: 3.7
Classifier: Operating System :: OS Independent
Classifier: License :: OSI Approved :: MIT License
Requires-Python: >=3.6
Requires-Dist: pytest (>=4.0.0)
